scotplus/__init__.py
scotplus/solvers.py
scotplus/backend/package_solver_supervised.py
scotplus/utils/alignment.py
scotplus-1.0.2.dist-info/LICENSE
scotplus-1.0.2.dist-info/METADATA
scotplus-1.0.2.dist-info/WHEEL
scotplus-1.0.2.dist-info/top_level.txt
scotplus-1.0.2.dist-info/RECORD
